{
    "datetime": 1676803303,
    "donate_url": "https://paypal.me/lukew594",
    "error": false,
    "filehash": "2168e0f0889d1e57a851ba7ea7e84c09",
    "filename": "evolution_beyond2lte-ota-tq1a.230205.002-02191042-community-unsigned.zip",
    "forum_url": "https://forum.xda-developers.com/t/rom-13-encryption-evolution-x-7-x-for-samsung-galaxy-s10e-s10-s10-s10-5g.4531403/",
    "id": "48fa7873c0b086bb818b2826320aa5ac18963c645cd5813d4a4d3b051360dee4",
    "maintainer": "ExpressLuke",
    "maintainer_url": "https://forum.xda-developers.com/m/expressluke.7166349/",
    "news_url": "1896003972",
    "size": "OGExpressLuke",
    "telegram_username": "Thirteen",
    "url": "https://evolution-x.org",
    "version": "",
    "website_url": ""
}
