{
    "datetime": 1699699807,
    "donate_url": "https://paypal.me/lukew594",
    "error": false,
    "filehash": "9755a41956a84ce52cd2623cdbcae002",
    "filename": "evolution_dreamlte-ota-tq3c.230901.001.b1-11111051-community-unsigned.zip",
    "forum_url": "https://expresserino.github.io/evo-downloads.html",
    "id": "7770207c7b21d889369f35ff9bac1a71ab2a87f802843dbfa964426b6471d60c",
    "maintainer": "ExpressLuke",
    "maintainer_url": "https://forum.xda-developers.com/m/expressluke.7166349/",
    "news_url": "https://t.me/EvolutionXOfficial",
    "size": 1778451024,
    "telegram_username": "expressluke",
    "url": "https://github.com/Evolution-X-Exynos/OTA/releases/download/evolution_dreamlte-ota-tq3c.230901.001.b1-11111051-community-unsigned.zip/evolution_dreamlte-ota-tq3c.230901.001.b1-11111051-community-unsigned.zip",
    "version": "Thirteen",
    "website_url": "https://evolution-x.org"
}
